Neron/__init__.py
Neron-0.0.0.dist-info/METADATA
Neron-0.0.0.dist-info/WHEEL
Neron-0.0.0.dist-info/top_level.txt
Neron-0.0.0.dist-info/RECORD
