Metadata-Version: 2.1
Name: Neron
Version: 0.0.0
Summary: A Python wrapper for the Neron API
Home-page: https://github.com/NeronApp/PythonPublicAPI
Author: Neron
License: UNKNOWN
Platform: UNKNOWN
Requires-Python: >= 3.6
